hask/Haskell/Prelude/__init__.py
hask/Haskell/Prelude/infix.pyi
hask/Haskell/__init__.py
hask/Prettyprinter/Internal.py
hask/Prettyprinter/Render/String.py
hask/Prettyprinter/Render/Text.py
hask/Prettyprinter/Render/Util/Panic.py
hask/Prettyprinter/Render/Util/__init__.py
hask/Prettyprinter/Render/__init__.py
hask/Prettyprinter/Symbols/Ascii.py
hask/Prettyprinter/Symbols/Unicode.py
hask/Prettyprinter/Symbols/__init__.py
hask/Prettyprinter/Util.py
hask/Prettyprinter/__init__.py
hask/System/IO/__init__.py
hask/System/__init__.py
hask/__init__.py
hask/infix.py
hask/runtime.py
hask/typing.py
hask-0.3.0.dist-info/LICENSE
hask-0.3.0.dist-info/WHEEL
hask-0.3.0.dist-info/METADATA
hask-0.3.0.dist-info/RECORD
